purekit/__init__.py
purekit/enums.py
purekit/exceptions.py
purekit/fn.py
purekit/meta.py
purekit/num.py
purekit/py.typed
purekit/seq.py
purekit/sets.py
purekit/text.py
purekit-0.1.0rc4.dist-info/WHEEL
purekit-0.1.0rc4.dist-info/METADATA
purekit-0.1.0rc4.dist-info/RECORD
