Metadata-Version: 2.3
Name: purekit
Version: 0.1.0rc4
Summary: 
Author: oyghen
Author-email: oyghen <oyghen@duck.com>
Requires-Python: >=3.11
